MANIFEST.in
setup.py
masonite/contrib/digitalocean/__init__.py
masonite/contrib/digitalocean/drivers/UploadDigitaloceanDriver.py
masonite/contrib/digitalocean/drivers/__init__.py
masonite/contrib/digitalocean/providers/DigitalOceanProvider.py
masonite/contrib/digitalocean/providers/__init__.py
masonite_digitalocean_driver.egg-info/PKG-INFO
masonite_digitalocean_driver.egg-info/SOURCES.txt
masonite_digitalocean_driver.egg-info/dependency_links.txt
masonite_digitalocean_driver.egg-info/requires.txt
masonite_digitalocean_driver.egg-info/top_level.txt